{
    "WhitelistedUsers": {
        "530928013": {
            "hash": "7bd8c599e2026f12a0d5ac73baf86528b52e20a219ac7b9abc88c98b766dee481d40b6f3f058e089389abe36dd7cca3437e27b96fd4c11b3240aa92f0bb979f1",
            "attackable": false,
            "level": 7,
            "discord": {
                "userid": "1145068116007718952",
                "name": "new_qwertyui"
            },
            "tags": [
                {
                    "text": "SEAL",
                    "color": [
                        255,
                        255,
                        255
                    ]
                }
            ]
        },
        "2441909268": {
            "hash": "5257ebed36cee341e79cdf03f7fe40e94228d1c1343bf36cbd5eed46c02494bbce311c7979618aa2089ab9458a6792c108aaeb5dc58629de4de3245254f3ac92",
            "attackable": false,
            "level": 255,
            "discord": {
                "userid": "691944570312851556",
                "name": "maxlasertech"
            },
            "tags": [
                {
                    "text": "CAT OWNER",
                    "color": [
                        255,
                        255,
                        255
                    ]
                }
            ]
        },
        "9414124704": {
            "hash": "2489dd5918fc434f3eaf3723538556ab29d5f0f30b32f92d329c43387b39a6d7315c4493c437ca9c5c1c5a375d1ee1898cc423fd18121e0934042336bcc5b8ec",
            "attackable": false,
            "level": 9,
            "discord": {
                "userid": "1220712232095060008",
                "name": "1shaders"
            },
            "tags": [
                {
                    "text": "catvape admin",
                    "color": [
                        255,
                        255,
                        255
                    ]
                }
            ]
        },
        "9554231533": {
            "hash": "476f39e0c4684828dafcf0336e6fa4b95086a6094c079ebc780603de68f45f66fe4d54dd3554f871ac28f9bc8257cec7e8addc3e7ca69c8167002fce4c329c62",
            "attackable": false,
            "level": 1,
            "discord": {
                "userid": "1346961223039586467",
                "name": "1stplacewarrior"
            },
            "tags": [
                {
                    "text": "PISTONWARE OWNER",
                    "color": [
                        255,
                        255,
                        255
                    ]
                }
            ]
        },
        "9572859732": {
            "hash": "5295142ef786ed64b0a68ac6459c45ee4d348607766336dee5e5dc82748cbdb879df7404fe6a4d8539387fdfc57dbb9ccf921937aa58023884b2cd0deed7f837",
            "attackable": false,
            "level": 1,
            "discord": {
                "userid": "1346961223039586467",
                "name": "1stplacewarrior"
            },
            "tags": [
                {
                    "text": "PISTONWARE OWNER",
                    "color": [
                        255,
                        255,
                        255
                    ]
                }
            ]
        },
        "9608535215": {
            "hash": "95d2b8038f92347193772a2bd4d7ff592037f60e8ee90dd90c9d1ac82e00c251405b7e2f9ff3ec5ac3dfa1f0282caa5d039d93e5e8a4bfc0dac5c1614ea903b6",
            "attackable": false,
            "level": 1,
            "discord": {
                "userid": "1346961223039586467",
                "name": "1stplacewarrior"
            },
            "tags": [
                {
                    "text": "PISTONWARE OWNER",
                    "color": [
                        255,
                        255,
                        255
                    ]
                }
            ]
        },
        "9615080599": {
            "hash": "26995d317bff2aff0a75eb43d4c4aedae8fd5d918618e6a74e7a419d0a61b4c21450d3d84df08d05e701d31e688bafd8a7493dbda1abeddf52e564353400cfb8",
            "attackable": false,
            "level": 1,
            "discord": {
                "userid": "1346961223039586467",
                "name": "1stplacewarrior"
            },
            "tags": [
                {
                    "text": "PISTONWARE OWNER",
                    "color": [
                        255,
                        255,
                        255
                    ]
                }
            ]
        },
        "4162465388": {
            "hash": "9318cb5c4e1a1c13ac1e15f5dbbb4369a6ca7f1b6746a18788ced91b7c8ba2752fe951e883a8e6ae949ecedac4f93f05917f6b4a750fd1fa15978927d5d06703",
            "attackable": false,
            "level": 2,
            "discord": {
                "userid": "1220712232095060008",
                "name": "1shaders"
            },
            "tags": [
                {
                    "text": "catvape admin",
                    "color": [
                        255,
                        255,
                        255
                    ]
                }
            ]
        }
    }
}