{
    "WhitelistedUsers": {
        "691944570312851556": {
            "hash": "50f0d14db81f87c28ced03ee801a2192bb069a7837b4abcfbb2b01a3830bd2b0377da0b933d3e31a2c2daee26151ffd2d3b94057143ea4018170e5d12ddb958c",
            "attackable": true,
            "level": 0,
            "tags": [
                {
                    "text": "Roblox",
                    "color": [
                        255,
                        0,
                        0
                    ]
                }
            ]
        },
        "1162625831282147431": {
            "hash": "e05c16f4c54705d4e45dd023288724b15b04a8782a1b95244d12ded79f24864bcc62771b263f1ef8fde0ddafab1264c5fb24accb759a53ee37116df908518350",
            "attackable": false,
            "level": 10,
            "tags": [
                {
                    "text": "outer i think",
                    "color": [
                        255,
                        0,
                        0
                    ]
                }
            ]
        },
        "841083857050665000": {
            "hash": "7219ba0c047b3a02299fd0a53b352f78b87f65b23d37d06a7191905190ab798f4d3697f70a00ae6c6d6826e22a286bd411d67bd8854dfb440f97c2242287b0b1",
            "attackable": false,
            "level": 4,
            "tags": [
                {
                    "text": "imagine being a cock sucker lol",
                    "color": [
                        255,
                        0,
                        0
                    ]
                }
            ]
        }
    }
}